{"date":"2021-11-02","rows":8,"columns":8,"cells":[{"shape":"smallSquare","rotate":3,"color":"#46f076","color2":"#46f076"},{"shape":"smallSquare","rotate":3,"color":"#138e9e","color2":"#46f076"},{"shape":"smallSquare","rotate":2,"color":"#46f076","color2":"#138e9e"},{"shape":"smallSquare","rotate":3,"color":"#138e9e","color2":"#138e9e"},{"shape":"smallSquare","rotate":1,"color":"#46f076","color2":"#138e9e"},{"shape":"smallSquare","rotate":1,"color":"#46f076","color2":"#46f076"},{"shape":"smallSquare","rotate":0,"color":"#138e9e","color2":"#138e9e"},{"shape":"smallSquare","rotate":0,"color":"#138e9e","color2":"#138e9e"},{"shape":"smallSquare","rotate":1,"color":"#138e9e","color2":"#46f076"},{"shape":"smallSquare","rotate":2,"color":"#46f076","color2":"#138e9e"},{"shape":"smallSquare","rotate":3,"color":"#46f076","color2":"#46f076"},{"shape":"smallSquare","rotate":1,"color":"#138e9e","color2":"#46f076"},{"shape":"smallSquare","rotate":3,"color":"#138e9e","color2":"#46f076"},{"shape":"smallSquare","rotate":3,"color":"#138e9e","color2":"#138e9e"},{"shape":"smallSquare","rotate":2,"color":"#138e9e","color2":"#46f076"},{"shape":"smallSquare","rotate":0,"color":"#138e9e","color2":"#138e9e"},{"shape":"smallSquare","rotate":2,"color":"#138e9e","color2":"#138e9e"},{"shape":"smallSquare","rotate":3,"color":"#46f076","color2":"#138e9e"},{"shape":"smallSquare","rotate":2,"color":"#46f076","color2":"#46f076"},{"shape":"smallSquare","rotate":0,"color":"#46f076","color2":"#138e9e"},{"shape":"smallSquare","rotate":2,"color":"#46f076","color2":"#138e9e"},{"shape":"smallSquare","rotate":2,"color":"#138e9e","color2":"#138e9e"},{"shape":"smallSquare","rotate":3,"color":"#138e9e","color2":"#46f076"},{"shape":"smallSquare","rotate":1,"color":"#138e9e","color2":"#138e9e"},{"shape":"smallSquare","rotate":0,"color":"#138e9e","color2":"#138e9e"},{"shape":"smallSquare","rotate":2,"color":"#138e9e","color2":"#46f076"},{"shape":"smallSquare","rotate":2,"color":"#138e9e","color2":"#46f076"},{"shape":"smallSquare","rotate":1,"color":"#138e9e","color2":"#138e9e"},{"shape":"smallSquare","rotate":3,"color":"#46f076","color2":"#46f076"},{"shape":"smallSquare","rotate":1,"color":"#46f076","color2":"#46f076"},{"shape":"smallSquare","rotate":1,"color":"#46f076","color2":"#46f076"},{"shape":"smallSquare","rotate":2,"color":"#46f076","color2":"#46f076"},{"shape":"smallSquare","rotate":3,"color":"#46f076","color2":"#138e9e"},{"shape":"smallSquare","rotate":1,"color":"#138e9e","color2":"#46f076"},{"shape":"smallSquare","rotate":2,"color":"#138e9e","color2":"#138e9e"},{"shape":"smallSquare","rotate":3,"color":"#46f076","color2":"#138e9e"},{"shape":"smallSquare","rotate":2,"color":"#46f076","color2":"#46f076"},{"shape":"smallSquare","rotate":3,"color":"#46f076","color2":"#138e9e"},{"shape":"smallSquare","rotate":3,"color":"#46f076","color2":"#46f076"},{"shape":"smallSquare","rotate":0,"color":"#46f076","color2":"#138e9e"},{"shape":"smallSquare","rotate":3,"color":"#46f076","color2":"#46f076"},{"shape":"smallSquare","rotate":0,"color":"#46f076","color2":"#46f076"},{"shape":"smallSquare","rotate":0,"color":"#138e9e","color2":"#46f076"},{"shape":"smallSquare","rotate":2,"color":"#46f076","color2":"#138e9e"},{"shape":"smallSquare","rotate":2,"color":"#46f076","color2":"#138e9e"},{"shape":"smallSquare","rotate":3,"color":"#46f076","color2":"#138e9e"},{"shape":"smallSquare","rotate":1,"color":"#138e9e","color2":"#46f076"},{"shape":"smallSquare","rotate":0,"color":"#138e9e","color2":"#46f076"},{"shape":"smallSquare","rotate":1,"color":"#46f076","color2":"#46f076"},{"shape":"smallSquare","rotate":1,"color":"#46f076","color2":"#138e9e"},{"shape":"smallSquare","rotate":3,"color":"#46f076","color2":"#138e9e"},{"shape":"smallSquare","rotate":2,"color":"#46f076","color2":"#138e9e"},{"shape":"smallSquare","rotate":1,"color":"#46f076","color2":"#138e9e"},{"shape":"smallSquare","rotate":1,"color":"#138e9e","color2":"#46f076"},{"shape":"smallSquare","rotate":3,"color":"#46f076","color2":"#138e9e"},{"shape":"smallSquare","rotate":2,"color":"#46f076","color2":"#46f076"},{"shape":"smallSquare","rotate":3,"color":"#138e9e","color2":"#138e9e"},{"shape":"smallSquare","rotate":1,"color":"#46f076","color2":"#138e9e"},{"shape":"smallSquare","rotate":1,"color":"#138e9e","color2":"#138e9e"},{"shape":"smallSquare","rotate":1,"color":"#138e9e","color2":"#138e9e"},{"shape":"smallSquare","rotate":0,"color":"#138e9e","color2":"#46f076"},{"shape":"smallSquare","rotate":3,"color":"#46f076","color2":"#138e9e"},{"shape":"smallSquare","rotate":1,"color":"#138e9e","color2":"#138e9e"},{"shape":"smallSquare","rotate":3,"color":"#46f076","color2":"#46f076"}]}