{"date":"2021-12-16","rows":5,"columns":5,"cells":[{"shape":"curved","rotate":2,"color":"#fa73cf","color2":"#eb96b9"},{"shape":"curved","rotate":0,"color":"#fa73cf","color2":"#eb96b9"},{"shape":"curved","rotate":2,"color":"#eb96b9","color2":"#eb96b9"},{"shape":"curved","rotate":0,"color":"#eb96b9","color2":"#fa73cf"},{"shape":"curved","rotate":3,"color":"#caaff0","color2":"#fa73cf"},{"shape":"curved","rotate":3,"color":"#eb96b9","color2":"#fa73cf"},{"shape":"curved","rotate":0,"color":"#fa73cf","color2":"#fa73cf"},{"shape":"curved","rotate":2,"color":"#eb96b9","color2":"#caaff0"},{"shape":"curved","rotate":1,"color":"#eb96b9","color2":"#caaff0"},{"shape":"curved","rotate":2,"color":"#fa73cf","color2":"#fa73cf"},{"shape":"curved","rotate":2,"color":"#fa73cf","color2":"#caaff0"},{"shape":"curved","rotate":3,"color":"#eb96b9","color2":"#fa73cf"},{"shape":"curved","rotate":0,"color":"#eb96b9","color2":"#eb96b9"},{"shape":"curved","rotate":2,"color":"#fa73cf","color2":"#fa73cf"},{"shape":"curved","rotate":2,"color":"#eb96b9","color2":"#eb96b9"},{"shape":"curved","rotate":1,"color":"#eb96b9","color2":"#fa73cf"},{"shape":"curved","rotate":2,"color":"#fa73cf","color2":"#fa73cf"},{"shape":"curved","rotate":3,"color":"#eb96b9","color2":"#fa73cf"},{"shape":"curved","rotate":0,"color":"#caaff0","color2":"#caaff0"},{"shape":"curved","rotate":0,"color":"#fa73cf","color2":"#eb96b9"},{"shape":"curved","rotate":0,"color":"#fa73cf","color2":"#eb96b9"},{"shape":"curved","rotate":1,"color":"#fa73cf","color2":"#eb96b9"},{"shape":"curved","rotate":0,"color":"#caaff0","color2":"#fa73cf"},{"shape":"curved","rotate":0,"color":"#fa73cf","color2":"#eb96b9"},{"shape":"curved","rotate":2,"color":"#fa73cf","color2":"#fa73cf"}]}