{"date":"2022-01-22","rows":5,"columns":5,"cells":[{"shape":"skewed","rotate":2,"color":"#48d49c","color2":"#48d49c"},{"shape":"skewed","rotate":3,"color":"#d647cf","color2":"#440a94"},{"shape":"skewed","rotate":2,"color":"#48d49c","color2":"#48d49c"},{"shape":"skewed","rotate":3,"color":"#48d49c","color2":"#48d49c"},{"shape":"skewed","rotate":2,"color":"#48d49c","color2":"#48d49c"},{"shape":"skewed","rotate":2,"color":"#440a94","color2":"#48d49c"},{"shape":"skewed","rotate":3,"color":"#440a94","color2":"#48d49c"},{"shape":"skewed","rotate":3,"color":"#440a94","color2":"#d647cf"},{"shape":"skewed","rotate":0,"color":"#d647cf","color2":"#440a94"},{"shape":"skewed","rotate":0,"color":"#48d49c","color2":"#d647cf"},{"shape":"skewed","rotate":3,"color":"#d647cf","color2":"#440a94"},{"shape":"skewed","rotate":3,"color":"#48d49c","color2":"#d647cf"},{"shape":"skewed","rotate":1,"color":"#48d49c","color2":"#d647cf"},{"shape":"skewed","rotate":3,"color":"#d647cf","color2":"#48d49c"},{"shape":"skewed","rotate":0,"color":"#48d49c","color2":"#48d49c"},{"shape":"skewed","rotate":1,"color":"#48d49c","color2":"#440a94"},{"shape":"skewed","rotate":0,"color":"#48d49c","color2":"#48d49c"},{"shape":"skewed","rotate":2,"color":"#d647cf","color2":"#d647cf"},{"shape":"skewed","rotate":1,"color":"#d647cf","color2":"#48d49c"},{"shape":"skewed","rotate":0,"color":"#d647cf","color2":"#440a94"},{"shape":"skewed","rotate":0,"color":"#440a94","color2":"#440a94"},{"shape":"skewed","rotate":3,"color":"#440a94","color2":"#48d49c"},{"shape":"skewed","rotate":3,"color":"#440a94","color2":"#440a94"},{"shape":"skewed","rotate":1,"color":"#440a94","color2":"#48d49c"},{"shape":"skewed","rotate":2,"color":"#440a94","color2":"#d647cf"}]}