{"date":"2023-01-19","rows":12,"columns":12,"cells":[{"shape":"circle","rotate":3,"color":"#ffffbf","color2":"#f5b5f3"},{"shape":"circle","rotate":2,"color":"#ffffbf","color2":"#ffffbf"},{"shape":"circle","rotate":0,"color":"#d1bcf7","color2":"#f5b5f3"},{"shape":"circle","rotate":1,"color":"#f5b5f3","color2":"#f5b5f3"},{"shape":"circle","rotate":2,"color":"#3194a8","color2":"#3194a8"},{"shape":"circle","rotate":0,"color":"#ffffbf","color2":"#f5b5f3"},{"shape":"circle","rotate":2,"color":"#ffffbf","color2":"#f5b5f3"},{"shape":"circle","rotate":3,"color":"#3194a8","color2":"#d1bcf7"},{"shape":"circle","rotate":0,"color":"#f5b5f3","color2":"#f5b5f3"},{"shape":"circle","rotate":1,"color":"#f5b5f3","color2":"#3194a8"},{"shape":"circle","rotate":2,"color":"#f5b5f3","color2":"#d1bcf7"},{"shape":"circle","rotate":2,"color":"#d1bcf7","color2":"#d1bcf7"},{"shape":"circle","rotate":3,"color":"#f5b5f3","color2":"#f5b5f3"},{"shape":"circle","rotate":1,"color":"#ffffbf","color2":"#3194a8"},{"shape":"circle","rotate":3,"color":"#f5b5f3","color2":"#f5b5f3"},{"shape":"circle","rotate":0,"color":"#3194a8","color2":"#ffffbf"},{"shape":"circle","rotate":0,"color":"#ffffbf","color2":"#d1bcf7"},{"shape":"circle","rotate":3,"color":"#d1bcf7","color2":"#ffffbf"},{"shape":"circle","rotate":0,"color":"#f5b5f3","color2":"#d1bcf7"},{"shape":"circle","rotate":2,"color":"#f5b5f3","color2":"#3194a8"},{"shape":"circle","rotate":1,"color":"#f5b5f3","color2":"#f5b5f3"},{"shape":"circle","rotate":0,"color":"#3194a8","color2":"#f5b5f3"},{"shape":"circle","rotate":1,"color":"#f5b5f3","color2":"#f5b5f3"},{"shape":"circle","rotate":1,"color":"#3194a8","color2":"#ffffbf"},{"shape":"circle","rotate":1,"color":"#3194a8","color2":"#ffffbf"},{"shape":"circle","rotate":3,"color":"#d1bcf7","color2":"#3194a8"},{"shape":"circle","rotate":3,"color":"#f5b5f3","color2":"#d1bcf7"},{"shape":"circle","rotate":2,"color":"#ffffbf","color2":"#d1bcf7"},{"shape":"circle","rotate":1,"color":"#3194a8","color2":"#3194a8"},{"shape":"circle","rotate":2,"color":"#d1bcf7","color2":"#ffffbf"},{"shape":"circle","rotate":2,"color":"#ffffbf","color2":"#f5b5f3"},{"shape":"circle","rotate":1,"color":"#3194a8","color2":"#f5b5f3"},{"shape":"circle","rotate":2,"color":"#d1bcf7","color2":"#d1bcf7"},{"shape":"circle","rotate":1,"color":"#3194a8","color2":"#d1bcf7"},{"shape":"circle","rotate":1,"color":"#d1bcf7","color2":"#ffffbf"},{"shape":"circle","rotate":2,"color":"#d1bcf7","color2":"#3194a8"},{"shape":"circle","rotate":0,"color":"#d1bcf7","color2":"#f5b5f3"},{"shape":"circle","rotate":2,"color":"#3194a8","color2":"#ffffbf"},{"shape":"circle","rotate":2,"color":"#3194a8","color2":"#d1bcf7"},{"shape":"circle","rotate":2,"color":"#3194a8","color2":"#ffffbf"},{"shape":"circle","rotate":2,"color":"#f5b5f3","color2":"#d1bcf7"},{"shape":"circle","rotate":0,"color":"#3194a8","color2":"#f5b5f3"},{"shape":"circle","rotate":1,"color":"#f5b5f3","color2":"#ffffbf"},{"shape":"circle","rotate":1,"color":"#ffffbf","color2":"#3194a8"},{"shape":"circle","rotate":2,"color":"#3194a8","color2":"#d1bcf7"},{"shape":"circle","rotate":3,"color":"#ffffbf","color2":"#d1bcf7"},{"shape":"circle","rotate":1,"color":"#ffffbf","color2":"#3194a8"},{"shape":"circle","rotate":1,"color":"#3194a8","color2":"#f5b5f3"},{"shape":"circle","rotate":1,"color":"#ffffbf","color2":"#d1bcf7"},{"shape":"circle","rotate":2,"color":"#f5b5f3","color2":"#d1bcf7"},{"shape":"circle","rotate":2,"color":"#f5b5f3","color2":"#3194a8"},{"shape":"circle","rotate":0,"color":"#ffffbf","color2":"#3194a8"},{"shape":"circle","rotate":0,"color":"#ffffbf","color2":"#ffffbf"},{"shape":"circle","rotate":3,"color":"#f5b5f3","color2":"#3194a8"},{"shape":"circle","rotate":1,"color":"#f5b5f3","color2":"#3194a8"},{"shape":"circle","rotate":3,"color":"#d1bcf7","color2":"#ffffbf"},{"shape":"circle","rotate":0,"color":"#ffffbf","color2":"#f5b5f3"},{"shape":"circle","rotate":0,"color":"#ffffbf","color2":"#f5b5f3"},{"shape":"circle","rotate":1,"color":"#d1bcf7","color2":"#f5b5f3"},{"shape":"circle","rotate":0,"color":"#d1bcf7","color2":"#f5b5f3"},{"shape":"circle","rotate":0,"color":"#ffffbf","color2":"#f5b5f3"},{"shape":"circle","rotate":0,"color":"#3194a8","color2":"#f5b5f3"},{"shape":"circle","rotate":3,"color":"#ffffbf","color2":"#ffffbf"},{"shape":"circle","rotate":3,"color":"#ffffbf","color2":"#d1bcf7"},{"shape":"circle","rotate":2,"color":"#ffffbf","color2":"#3194a8"},{"shape":"circle","rotate":1,"color":"#d1bcf7","color2":"#f5b5f3"},{"shape":"circle","rotate":1,"color":"#d1bcf7","color2":"#d1bcf7"},{"shape":"circle","rotate":2,"color":"#f5b5f3","color2":"#ffffbf"},{"shape":"circle","rotate":1,"color":"#ffffbf","color2":"#ffffbf"},{"shape":"circle","rotate":2,"color":"#ffffbf","color2":"#d1bcf7"},{"shape":"circle","rotate":2,"color":"#d1bcf7","color2":"#ffffbf"},{"shape":"circle","rotate":2,"color":"#f5b5f3","color2":"#f5b5f3"},{"shape":"circle","rotate":1,"color":"#d1bcf7","color2":"#3194a8"},{"shape":"circle","rotate":3,"color":"#d1bcf7","color2":"#f5b5f3"},{"shape":"circle","rotate":1,"color":"#3194a8","color2":"#ffffbf"},{"shape":"circle","rotate":1,"color":"#d1bcf7","color2":"#d1bcf7"},{"shape":"circle","rotate":2,"color":"#d1bcf7","color2":"#d1bcf7"},{"shape":"circle","rotate":3,"color":"#ffffbf","color2":"#ffffbf"},{"shape":"circle","rotate":3,"color":"#f5b5f3","color2":"#ffffbf"},{"shape":"circle","rotate":3,"color":"#ffffbf","color2":"#ffffbf"},{"shape":"circle","rotate":2,"color":"#ffffbf","color2":"#f5b5f3"},{"shape":"circle","rotate":3,"color":"#d1bcf7","color2":"#f5b5f3"},{"shape":"circle","rotate":2,"color":"#ffffbf","color2":"#ffffbf"},{"shape":"circle","rotate":0,"color":"#f5b5f3","color2":"#f5b5f3"},{"shape":"circle","rotate":2,"color":"#d1bcf7","color2":"#ffffbf"},{"shape":"circle","rotate":0,"color":"#d1bcf7","color2":"#f5b5f3"},{"shape":"circle","rotate":3,"color":"#ffffbf","color2":"#3194a8"},{"shape":"circle","rotate":0,"color":"#f5b5f3","color2":"#d1bcf7"},{"shape":"circle","rotate":0,"color":"#f5b5f3","color2":"#3194a8"},{"shape":"circle","rotate":3,"color":"#f5b5f3","color2":"#3194a8"},{"shape":"circle","rotate":3,"color":"#d1bcf7","color2":"#ffffbf"},{"shape":"circle","rotate":1,"color":"#3194a8","color2":"#3194a8"},{"shape":"circle","rotate":0,"color":"#d1bcf7","color2":"#ffffbf"},{"shape":"circle","rotate":1,"color":"#f5b5f3","color2":"#f5b5f3"},{"shape":"circle","rotate":3,"color":"#ffffbf","color2":"#f5b5f3"},{"shape":"circle","rotate":3,"color":"#3194a8","color2":"#d1bcf7"},{"shape":"circle","rotate":3,"color":"#ffffbf","color2":"#ffffbf"},{"shape":"circle","rotate":2,"color":"#d1bcf7","color2":"#3194a8"},{"shape":"circle","rotate":2,"color":"#d1bcf7","color2":"#d1bcf7"},{"shape":"circle","rotate":0,"color":"#3194a8","color2":"#ffffbf"},{"shape":"circle","rotate":0,"color":"#3194a8","color2":"#ffffbf"},{"shape":"circle","rotate":2,"color":"#f5b5f3","color2":"#ffffbf"},{"shape":"circle","rotate":0,"color":"#3194a8","color2":"#ffffbf"},{"shape":"circle","rotate":1,"color":"#f5b5f3","color2":"#d1bcf7"},{"shape":"circle","rotate":1,"color":"#f5b5f3","color2":"#f5b5f3"},{"shape":"circle","rotate":3,"color":"#ffffbf","color2":"#f5b5f3"},{"shape":"circle","rotate":0,"color":"#d1bcf7","color2":"#d1bcf7"},{"shape":"circle","rotate":2,"color":"#ffffbf","color2":"#f5b5f3"},{"shape":"circle","rotate":2,"color":"#ffffbf","color2":"#d1bcf7"},{"shape":"circle","rotate":1,"color":"#ffffbf","color2":"#d1bcf7"},{"shape":"circle","rotate":2,"color":"#3194a8","color2":"#ffffbf"},{"shape":"circle","rotate":2,"color":"#d1bcf7","color2":"#ffffbf"},{"shape":"circle","rotate":3,"color":"#ffffbf","color2":"#f5b5f3"},{"shape":"circle","rotate":3,"color":"#f5b5f3","color2":"#d1bcf7"},{"shape":"circle","rotate":0,"color":"#ffffbf","color2":"#f5b5f3"},{"shape":"circle","rotate":1,"color":"#ffffbf","color2":"#d1bcf7"},{"shape":"circle","rotate":2,"color":"#d1bcf7","color2":"#ffffbf"},{"shape":"circle","rotate":3,"color":"#3194a8","color2":"#ffffbf"},{"shape":"circle","rotate":1,"color":"#ffffbf","color2":"#d1bcf7"},{"shape":"circle","rotate":0,"color":"#d1bcf7","color2":"#f5b5f3"},{"shape":"circle","rotate":2,"color":"#3194a8","color2":"#3194a8"},{"shape":"circle","rotate":0,"color":"#d1bcf7","color2":"#d1bcf7"},{"shape":"circle","rotate":3,"color":"#f5b5f3","color2":"#3194a8"},{"shape":"circle","rotate":1,"color":"#d1bcf7","color2":"#d1bcf7"},{"shape":"circle","rotate":0,"color":"#d1bcf7","color2":"#3194a8"},{"shape":"circle","rotate":1,"color":"#f5b5f3","color2":"#ffffbf"},{"shape":"circle","rotate":2,"color":"#3194a8","color2":"#3194a8"},{"shape":"circle","rotate":1,"color":"#ffffbf","color2":"#ffffbf"},{"shape":"circle","rotate":2,"color":"#ffffbf","color2":"#ffffbf"},{"shape":"circle","rotate":0,"color":"#ffffbf","color2":"#f5b5f3"},{"shape":"circle","rotate":2,"color":"#d1bcf7","color2":"#3194a8"},{"shape":"circle","rotate":2,"color":"#f5b5f3","color2":"#ffffbf"},{"shape":"circle","rotate":2,"color":"#d1bcf7","color2":"#3194a8"},{"shape":"circle","rotate":3,"color":"#ffffbf","color2":"#d1bcf7"},{"shape":"circle","rotate":3,"color":"#3194a8","color2":"#ffffbf"},{"shape":"circle","rotate":0,"color":"#3194a8","color2":"#ffffbf"},{"shape":"circle","rotate":0,"color":"#d1bcf7","color2":"#d1bcf7"},{"shape":"circle","rotate":1,"color":"#f5b5f3","color2":"#3194a8"},{"shape":"circle","rotate":0,"color":"#3194a8","color2":"#d1bcf7"},{"shape":"circle","rotate":3,"color":"#ffffbf","color2":"#d1bcf7"},{"shape":"circle","rotate":2,"color":"#d1bcf7","color2":"#3194a8"},{"shape":"circle","rotate":2,"color":"#d1bcf7","color2":"#ffffbf"},{"shape":"circle","rotate":1,"color":"#d1bcf7","color2":"#d1bcf7"},{"shape":"circle","rotate":0,"color":"#ffffbf","color2":"#ffffbf"}]}