{"date":"2023-04-08","rows":12,"columns":12,"cells":[{"shape":"triangle","rotate":3,"color":"#faafb6","color2":"#4cb833"},{"shape":"triangle","rotate":1,"color":"#faafb6","color2":"#faafb6"},{"shape":"triangle","rotate":0,"color":"#4cb833","color2":"#4cb833"},{"shape":"triangle","rotate":2,"color":"#faafb6","color2":"#4cb833"},{"shape":"triangle","rotate":1,"color":"#4cb833","color2":"#faafb6"},{"shape":"triangle","rotate":1,"color":"#faafb6","color2":"#4cb833"},{"shape":"triangle","rotate":1,"color":"#faafb6","color2":"#faafb6"},{"shape":"triangle","rotate":2,"color":"#faafb6","color2":"#faafb6"},{"shape":"triangle","rotate":2,"color":"#4cb833","color2":"#faafb6"},{"shape":"triangle","rotate":2,"color":"#4cb833","color2":"#4cb833"},{"shape":"triangle","rotate":3,"color":"#4cb833","color2":"#faafb6"},{"shape":"triangle","rotate":1,"color":"#4cb833","color2":"#faafb6"},{"shape":"triangle","rotate":0,"color":"#faafb6","color2":"#4cb833"},{"shape":"triangle","rotate":0,"color":"#4cb833","color2":"#faafb6"},{"shape":"triangle","rotate":3,"color":"#faafb6","color2":"#4cb833"},{"shape":"triangle","rotate":0,"color":"#faafb6","color2":"#4cb833"},{"shape":"triangle","rotate":0,"color":"#4cb833","color2":"#faafb6"},{"shape":"triangle","rotate":0,"color":"#faafb6","color2":"#4cb833"},{"shape":"triangle","rotate":1,"color":"#4cb833","color2":"#4cb833"},{"shape":"triangle","rotate":0,"color":"#4cb833","color2":"#4cb833"},{"shape":"triangle","rotate":0,"color":"#faafb6","color2":"#4cb833"},{"shape":"triangle","rotate":3,"color":"#4cb833","color2":"#faafb6"},{"shape":"triangle","rotate":0,"color":"#4cb833","color2":"#4cb833"},{"shape":"triangle","rotate":1,"color":"#4cb833","color2":"#4cb833"},{"shape":"triangle","rotate":0,"color":"#faafb6","color2":"#faafb6"},{"shape":"triangle","rotate":2,"color":"#4cb833","color2":"#4cb833"},{"shape":"triangle","rotate":0,"color":"#faafb6","color2":"#4cb833"},{"shape":"triangle","rotate":3,"color":"#faafb6","color2":"#4cb833"},{"shape":"triangle","rotate":2,"color":"#faafb6","color2":"#4cb833"},{"shape":"triangle","rotate":3,"color":"#4cb833","color2":"#faafb6"},{"shape":"triangle","rotate":1,"color":"#4cb833","color2":"#faafb6"},{"shape":"triangle","rotate":0,"color":"#4cb833","color2":"#faafb6"},{"shape":"triangle","rotate":0,"color":"#faafb6","color2":"#4cb833"},{"shape":"triangle","rotate":2,"color":"#4cb833","color2":"#faafb6"},{"shape":"triangle","rotate":1,"color":"#4cb833","color2":"#4cb833"},{"shape":"triangle","rotate":2,"color":"#4cb833","color2":"#4cb833"},{"shape":"triangle","rotate":1,"color":"#4cb833","color2":"#4cb833"},{"shape":"triangle","rotate":2,"color":"#4cb833","color2":"#4cb833"},{"shape":"triangle","rotate":3,"color":"#4cb833","color2":"#4cb833"},{"shape":"triangle","rotate":2,"color":"#4cb833","color2":"#4cb833"},{"shape":"triangle","rotate":1,"color":"#faafb6","color2":"#4cb833"},{"shape":"triangle","rotate":3,"color":"#faafb6","color2":"#faafb6"},{"shape":"triangle","rotate":1,"color":"#4cb833","color2":"#faafb6"},{"shape":"triangle","rotate":0,"color":"#4cb833","color2":"#faafb6"},{"shape":"triangle","rotate":3,"color":"#4cb833","color2":"#faafb6"},{"shape":"triangle","rotate":2,"color":"#faafb6","color2":"#faafb6"},{"shape":"triangle","rotate":1,"color":"#faafb6","color2":"#faafb6"},{"shape":"triangle","rotate":0,"color":"#faafb6","color2":"#faafb6"},{"shape":"triangle","rotate":0,"color":"#4cb833","color2":"#faafb6"},{"shape":"triangle","rotate":1,"color":"#faafb6","color2":"#4cb833"},{"shape":"triangle","rotate":2,"color":"#faafb6","color2":"#4cb833"},{"shape":"triangle","rotate":0,"color":"#4cb833","color2":"#4cb833"},{"shape":"triangle","rotate":2,"color":"#faafb6","color2":"#faafb6"},{"shape":"triangle","rotate":1,"color":"#4cb833","color2":"#4cb833"},{"shape":"triangle","rotate":1,"color":"#faafb6","color2":"#faafb6"},{"shape":"triangle","rotate":1,"color":"#faafb6","color2":"#faafb6"},{"shape":"triangle","rotate":1,"color":"#4cb833","color2":"#4cb833"},{"shape":"triangle","rotate":0,"color":"#faafb6","color2":"#faafb6"},{"shape":"triangle","rotate":1,"color":"#faafb6","color2":"#faafb6"},{"shape":"triangle","rotate":1,"color":"#faafb6","color2":"#4cb833"},{"shape":"triangle","rotate":1,"color":"#4cb833","color2":"#4cb833"},{"shape":"triangle","rotate":0,"color":"#4cb833","color2":"#faafb6"},{"shape":"triangle","rotate":1,"color":"#faafb6","color2":"#faafb6"},{"shape":"triangle","rotate":0,"color":"#4cb833","color2":"#4cb833"},{"shape":"triangle","rotate":2,"color":"#4cb833","color2":"#4cb833"},{"shape":"triangle","rotate":0,"color":"#faafb6","color2":"#4cb833"},{"shape":"triangle","rotate":3,"color":"#faafb6","color2":"#faafb6"},{"shape":"triangle","rotate":3,"color":"#faafb6","color2":"#4cb833"},{"shape":"triangle","rotate":1,"color":"#4cb833","color2":"#4cb833"},{"shape":"triangle","rotate":0,"color":"#4cb833","color2":"#4cb833"},{"shape":"triangle","rotate":3,"color":"#faafb6","color2":"#faafb6"},{"shape":"triangle","rotate":1,"color":"#4cb833","color2":"#faafb6"},{"shape":"triangle","rotate":1,"color":"#faafb6","color2":"#4cb833"},{"shape":"triangle","rotate":1,"color":"#4cb833","color2":"#4cb833"},{"shape":"triangle","rotate":3,"color":"#faafb6","color2":"#faafb6"},{"shape":"triangle","rotate":0,"color":"#faafb6","color2":"#4cb833"},{"shape":"triangle","rotate":0,"color":"#faafb6","color2":"#faafb6"},{"shape":"triangle","rotate":3,"color":"#faafb6","color2":"#4cb833"},{"shape":"triangle","rotate":1,"color":"#faafb6","color2":"#faafb6"},{"shape":"triangle","rotate":2,"color":"#4cb833","color2":"#4cb833"},{"shape":"triangle","rotate":0,"color":"#4cb833","color2":"#faafb6"},{"shape":"triangle","rotate":0,"color":"#faafb6","color2":"#faafb6"},{"shape":"triangle","rotate":3,"color":"#faafb6","color2":"#faafb6"},{"shape":"triangle","rotate":3,"color":"#4cb833","color2":"#4cb833"},{"shape":"triangle","rotate":3,"color":"#faafb6","color2":"#faafb6"},{"shape":"triangle","rotate":1,"color":"#faafb6","color2":"#faafb6"},{"shape":"triangle","rotate":0,"color":"#faafb6","color2":"#4cb833"},{"shape":"triangle","rotate":0,"color":"#4cb833","color2":"#4cb833"},{"shape":"triangle","rotate":1,"color":"#4cb833","color2":"#4cb833"},{"shape":"triangle","rotate":3,"color":"#faafb6","color2":"#4cb833"},{"shape":"triangle","rotate":0,"color":"#faafb6","color2":"#4cb833"},{"shape":"triangle","rotate":3,"color":"#faafb6","color2":"#4cb833"},{"shape":"triangle","rotate":2,"color":"#faafb6","color2":"#4cb833"},{"shape":"triangle","rotate":2,"color":"#faafb6","color2":"#4cb833"},{"shape":"triangle","rotate":3,"color":"#faafb6","color2":"#faafb6"},{"shape":"triangle","rotate":3,"color":"#faafb6","color2":"#faafb6"},{"shape":"triangle","rotate":2,"color":"#4cb833","color2":"#faafb6"},{"shape":"triangle","rotate":3,"color":"#4cb833","color2":"#4cb833"},{"shape":"triangle","rotate":0,"color":"#faafb6","color2":"#faafb6"},{"shape":"triangle","rotate":2,"color":"#faafb6","color2":"#4cb833"},{"shape":"triangle","rotate":3,"color":"#faafb6","color2":"#faafb6"},{"shape":"triangle","rotate":3,"color":"#faafb6","color2":"#4cb833"},{"shape":"triangle","rotate":0,"color":"#4cb833","color2":"#faafb6"},{"shape":"triangle","rotate":1,"color":"#4cb833","color2":"#faafb6"},{"shape":"triangle","rotate":2,"color":"#4cb833","color2":"#4cb833"},{"shape":"triangle","rotate":2,"color":"#4cb833","color2":"#4cb833"},{"shape":"triangle","rotate":2,"color":"#4cb833","color2":"#4cb833"},{"shape":"triangle","rotate":1,"color":"#faafb6","color2":"#4cb833"},{"shape":"triangle","rotate":2,"color":"#faafb6","color2":"#4cb833"},{"shape":"triangle","rotate":3,"color":"#4cb833","color2":"#faafb6"},{"shape":"triangle","rotate":3,"color":"#4cb833","color2":"#4cb833"},{"shape":"triangle","rotate":1,"color":"#faafb6","color2":"#faafb6"},{"shape":"triangle","rotate":2,"color":"#4cb833","color2":"#4cb833"},{"shape":"triangle","rotate":0,"color":"#faafb6","color2":"#4cb833"},{"shape":"triangle","rotate":1,"color":"#faafb6","color2":"#4cb833"},{"shape":"triangle","rotate":3,"color":"#4cb833","color2":"#faafb6"},{"shape":"triangle","rotate":2,"color":"#4cb833","color2":"#4cb833"},{"shape":"triangle","rotate":0,"color":"#4cb833","color2":"#faafb6"},{"shape":"triangle","rotate":2,"color":"#4cb833","color2":"#4cb833"},{"shape":"triangle","rotate":1,"color":"#4cb833","color2":"#faafb6"},{"shape":"triangle","rotate":1,"color":"#4cb833","color2":"#faafb6"},{"shape":"triangle","rotate":3,"color":"#4cb833","color2":"#4cb833"},{"shape":"triangle","rotate":3,"color":"#faafb6","color2":"#4cb833"},{"shape":"triangle","rotate":2,"color":"#faafb6","color2":"#4cb833"},{"shape":"triangle","rotate":0,"color":"#4cb833","color2":"#4cb833"},{"shape":"triangle","rotate":0,"color":"#4cb833","color2":"#faafb6"},{"shape":"triangle","rotate":2,"color":"#faafb6","color2":"#4cb833"},{"shape":"triangle","rotate":0,"color":"#4cb833","color2":"#4cb833"},{"shape":"triangle","rotate":0,"color":"#faafb6","color2":"#faafb6"},{"shape":"triangle","rotate":2,"color":"#4cb833","color2":"#faafb6"},{"shape":"triangle","rotate":2,"color":"#faafb6","color2":"#4cb833"},{"shape":"triangle","rotate":0,"color":"#4cb833","color2":"#4cb833"},{"shape":"triangle","rotate":2,"color":"#faafb6","color2":"#faafb6"},{"shape":"triangle","rotate":2,"color":"#faafb6","color2":"#faafb6"},{"shape":"triangle","rotate":0,"color":"#faafb6","color2":"#4cb833"},{"shape":"triangle","rotate":2,"color":"#faafb6","color2":"#4cb833"},{"shape":"triangle","rotate":2,"color":"#faafb6","color2":"#4cb833"},{"shape":"triangle","rotate":0,"color":"#4cb833","color2":"#4cb833"},{"shape":"triangle","rotate":3,"color":"#4cb833","color2":"#faafb6"},{"shape":"triangle","rotate":1,"color":"#faafb6","color2":"#faafb6"},{"shape":"triangle","rotate":2,"color":"#faafb6","color2":"#4cb833"},{"shape":"triangle","rotate":2,"color":"#faafb6","color2":"#faafb6"},{"shape":"triangle","rotate":2,"color":"#faafb6","color2":"#faafb6"},{"shape":"triangle","rotate":2,"color":"#faafb6","color2":"#faafb6"}]}