{"date":"2026-04-02","rows":6,"columns":6,"cells":[{"shape":"circle","rotate":3,"color":"#3e85a3","color2":"#f4ffab"},{"shape":"circle","rotate":1,"color":"#3e85a3","color2":"#f4ffab"},{"shape":"circle","rotate":2,"color":"#3e85a3","color2":"#3e85a3"},{"shape":"circle","rotate":2,"color":"#f4ffab","color2":"#3e85a3"},{"shape":"circle","rotate":1,"color":"#3e85a3","color2":"#f4ffab"},{"shape":"circle","rotate":3,"color":"#3e85a3","color2":"#3e85a3"},{"shape":"circle","rotate":1,"color":"#3e85a3","color2":"#f4ffab"},{"shape":"circle","rotate":0,"color":"#f4ffab","color2":"#f4ffab"},{"shape":"circle","rotate":1,"color":"#f4ffab","color2":"#3e85a3"},{"shape":"circle","rotate":1,"color":"#3e85a3","color2":"#3e85a3"},{"shape":"circle","rotate":3,"color":"#f4ffab","color2":"#f4ffab"},{"shape":"circle","rotate":0,"color":"#f4ffab","color2":"#3e85a3"},{"shape":"circle","rotate":1,"color":"#3e85a3","color2":"#3e85a3"},{"shape":"circle","rotate":3,"color":"#f4ffab","color2":"#3e85a3"},{"shape":"circle","rotate":3,"color":"#3e85a3","color2":"#3e85a3"},{"shape":"circle","rotate":2,"color":"#f4ffab","color2":"#f4ffab"},{"shape":"circle","rotate":0,"color":"#3e85a3","color2":"#3e85a3"},{"shape":"circle","rotate":2,"color":"#3e85a3","color2":"#f4ffab"},{"shape":"circle","rotate":2,"color":"#f4ffab","color2":"#f4ffab"},{"shape":"circle","rotate":1,"color":"#3e85a3","color2":"#f4ffab"},{"shape":"circle","rotate":1,"color":"#3e85a3","color2":"#3e85a3"},{"shape":"circle","rotate":1,"color":"#f4ffab","color2":"#3e85a3"},{"shape":"circle","rotate":1,"color":"#3e85a3","color2":"#f4ffab"},{"shape":"circle","rotate":2,"color":"#3e85a3","color2":"#f4ffab"},{"shape":"circle","rotate":3,"color":"#3e85a3","color2":"#3e85a3"},{"shape":"circle","rotate":2,"color":"#3e85a3","color2":"#3e85a3"},{"shape":"circle","rotate":2,"color":"#3e85a3","color2":"#f4ffab"},{"shape":"circle","rotate":1,"color":"#3e85a3","color2":"#3e85a3"},{"shape":"circle","rotate":0,"color":"#3e85a3","color2":"#3e85a3"},{"shape":"circle","rotate":2,"color":"#3e85a3","color2":"#3e85a3"},{"shape":"circle","rotate":1,"color":"#3e85a3","color2":"#f4ffab"},{"shape":"circle","rotate":2,"color":"#3e85a3","color2":"#f4ffab"},{"shape":"circle","rotate":2,"color":"#f4ffab","color2":"#3e85a3"},{"shape":"circle","rotate":2,"color":"#f4ffab","color2":"#3e85a3"},{"shape":"circle","rotate":1,"color":"#f4ffab","color2":"#3e85a3"},{"shape":"circle","rotate":1,"color":"#3e85a3","color2":"#3e85a3"}]}