{"date":"2026-01-30","rows":4,"columns":4,"cells":[{"shape":"smallCircle","rotate":1,"color":"#9e80e0","color2":"#fcbbee"},{"shape":"smallCircle","rotate":0,"color":"#9e80e0","color2":"#fcbbee"},{"shape":"smallCircle","rotate":0,"color":"#fcbbee","color2":"#9e80e0"},{"shape":"smallCircle","rotate":3,"color":"#9e80e0","color2":"#9e80e0"},{"shape":"smallCircle","rotate":2,"color":"#9e80e0","color2":"#fcbbee"},{"shape":"smallCircle","rotate":3,"color":"#fcbbee","color2":"#fcbbee"},{"shape":"smallCircle","rotate":3,"color":"#9e80e0","color2":"#fcbbee"},{"shape":"smallCircle","rotate":0,"color":"#9e80e0","color2":"#9e80e0"},{"shape":"smallCircle","rotate":3,"color":"#fcbbee","color2":"#9e80e0"},{"shape":"smallCircle","rotate":0,"color":"#9e80e0","color2":"#9e80e0"},{"shape":"smallCircle","rotate":3,"color":"#fcbbee","color2":"#9e80e0"},{"shape":"smallCircle","rotate":1,"color":"#fcbbee","color2":"#9e80e0"},{"shape":"smallCircle","rotate":0,"color":"#fcbbee","color2":"#9e80e0"},{"shape":"smallCircle","rotate":0,"color":"#fcbbee","color2":"#9e80e0"},{"shape":"smallCircle","rotate":1,"color":"#fcbbee","color2":"#9e80e0"},{"shape":"smallCircle","rotate":1,"color":"#fcbbee","color2":"#fcbbee"}]}